file_crud/__init__.py
file_crud/crud.py
file_crud-0.2.5.dist-info/licenses/license
file_crud-0.2.5.dist-info/METADATA
file_crud-0.2.5.dist-info/WHEEL
file_crud-0.2.5.dist-info/top_level.txt
file_crud-0.2.5.dist-info/RECORD
