Metadata-Version: 2.4
Name: file-crud
Version: 0.2.5
Summary: Simple CRUD operations for file handling in Python
Author: Frank Pineda
Author-email: fpineda11@gmail.com
Classifier: Programming Language :: Python :: 3
Classifier: License :: OSI Approved :: MIT License
Classifier: Operating System :: OS Independent
Requires-Python: >=3.6
License-File: license
Dynamic: author
Dynamic: author-email
Dynamic: classifier
Dynamic: description
Dynamic: description-content-type
Dynamic: license-file
Dynamic: requires-python
Dynamic: summary
